viptela_python/__init__.py
viptela_python/exceptions.py
viptela_python/viptela.py
viptela_python-0.5.11.dist-info/METADATA
viptela_python-0.5.11.dist-info/RECORD
viptela_python-0.5.11.dist-info/WHEEL
viptela_python-0.5.11.dist-info/top_level.txt
