Metadata-Version: 2.1
Name: viptela-python
Version: 0.5.11
Summary: This is the Cisco Viptela Python SDK
Home-page: https://github.com/eugene-ky-wong/viptela-python
Author: Eugene KY Wong
Author-email: morphyme@gmail.com
License: UNKNOWN
Platform: UNKNOWN
Classifier: Intended Audience :: Information Technology
Classifier: Intended Audience :: System Administrators
Classifier: Intended Audience :: Developers
Classifier: Programming Language :: Python :: 2.7
Classifier: License :: OSI Approved :: GNU General Public License v3 or later (GPLv3+)
Classifier: Operating System :: OS Independent
Classifier: Topic :: Utilities
Classifier: Topic :: Software Development :: Libraries :: Python Modules
Requires-Python: ~=2.7
Requires-Dist: requests
